bosdyn/__init__.py
bosdyn/api/__init__.py
bosdyn/api/alerts_pb2.py
bosdyn/api/alerts_pb2_grpc.py
bosdyn/api/arm_command_pb2.py
bosdyn/api/arm_command_pb2_grpc.py
bosdyn/api/arm_surface_contact_pb2.py
bosdyn/api/arm_surface_contact_pb2_grpc.py
bosdyn/api/arm_surface_contact_service_pb2.py
bosdyn/api/arm_surface_contact_service_pb2_grpc.py
bosdyn/api/audio_visual_pb2.py
bosdyn/api/audio_visual_pb2_grpc.py
bosdyn/api/audio_visual_service_pb2.py
bosdyn/api/audio_visual_service_pb2_grpc.py
bosdyn/api/auth_pb2.py
bosdyn/api/auth_pb2_grpc.py
bosdyn/api/auth_service_pb2.py
bosdyn/api/auth_service_pb2_grpc.py
bosdyn/api/basic_command_pb2.py
bosdyn/api/basic_command_pb2_grpc.py
bosdyn/api/bddf_pb2.py
bosdyn/api/bddf_pb2_grpc.py
bosdyn/api/data_acquisition_pb2.py
bosdyn/api/data_acquisition_pb2_grpc.py
bosdyn/api/data_acquisition_plugin_service_pb2.py
bosdyn/api/data_acquisition_plugin_service_pb2_grpc.py
bosdyn/api/data_acquisition_service_pb2.py
bosdyn/api/data_acquisition_service_pb2_grpc.py
bosdyn/api/data_acquisition_store_pb2.py
bosdyn/api/data_acquisition_store_pb2_grpc.py
bosdyn/api/data_acquisition_store_service_pb2.py
bosdyn/api/data_acquisition_store_service_pb2_grpc.py
bosdyn/api/data_buffer_pb2.py
bosdyn/api/data_buffer_pb2_grpc.py
bosdyn/api/data_buffer_service_pb2.py
bosdyn/api/data_buffer_service_pb2_grpc.py
bosdyn/api/data_chunk_pb2.py
bosdyn/api/data_chunk_pb2_grpc.py
bosdyn/api/data_index_pb2.py
bosdyn/api/data_index_pb2_grpc.py
bosdyn/api/data_service_pb2.py
bosdyn/api/data_service_pb2_grpc.py
bosdyn/api/directory_pb2.py
bosdyn/api/directory_pb2_grpc.py
bosdyn/api/directory_registration_pb2.py
bosdyn/api/directory_registration_pb2_grpc.py
bosdyn/api/directory_registration_service_pb2.py
bosdyn/api/directory_registration_service_pb2_grpc.py
bosdyn/api/directory_service_pb2.py
bosdyn/api/directory_service_pb2_grpc.py
bosdyn/api/estop_pb2.py
bosdyn/api/estop_pb2_grpc.py
bosdyn/api/estop_service_pb2.py
bosdyn/api/estop_service_pb2_grpc.py
bosdyn_api-5.0.1.dist-info/METADATA
bosdyn_api-5.0.1.dist-info/WHEEL
bosdyn_api-5.0.1.dist-info/top_level.txt
bosdyn_api-5.0.1.dist-info/RECORD
