Metadata-Version: 2.1
Name: bosdyn-api
Version: 5.0.1
Summary: Boston Dynamics API definition of protobuf messages
Home-page: https://dev.bostondynamics.com/
Author: Boston Dynamics
Author-email: support@bostondynamics.com
Project-URL: Documentation, https://dev.bostondynamics.com/
Project-URL: Source, https://github.com/boston-dynamics/spot-sdk/
Classifier: Programming Language :: Python :: 3.6
Classifier: Programming Language :: Python :: 3.7
Classifier: Programming Language :: Python :: 3.8
Classifier: Programming Language :: Python :: 3.9
Classifier: Programming Language :: Python :: 3.10
Classifier: License :: Other/Proprietary License
Classifier: Operating System :: OS Independent
Requires-Dist: protobuf (!=4.24.0,!=5.28.0,>=3.19.4)
